py4jrush/RuSH.py
py4jrush/Span.py
py4jrush/VERSION
py4jrush/__init__.py
py4jrush/version.py
py4jrush/conf/rush_rules.tsv
py4jrush/lib/py4j0.10.9.7.jar
py4jrush/lib/rush-2.0.0.0-jdk1.8-jar-with-dependencies.jar
py4jrush-1.0.13.dist-info/licenses/LICENSE
py4jrush-1.0.13.dist-info/METADATA
py4jrush-1.0.13.dist-info/WHEEL
py4jrush-1.0.13.dist-info/top_level.txt
py4jrush-1.0.13.dist-info/RECORD
