Metadata-Version: 2.4
Name: py4jrush
Version: 1.0.13
Summary: A fast implementation of RuSH (Rule-based sentence Segmenter using Hashing).
Home-page: https://github.com/jianlins/py4jrush
Author: Jianlin
Author-email: Jianlin <jianlinshi.cn@gmail.com>
License: MIT License
Project-URL: Source, https://github.com/jianlins/py4jrush
Keywords: ner,regex
Classifier: License :: OSI Approved :: MIT License
Classifier: Programming Language :: Python :: 3
Requires-Python: >=3.8
License-File: LICENSE
Requires-Dist: loguru>=0.5.0
Requires-Dist: setuptools
Requires-Dist: py4j
Requires-Dist: install-jdk
Dynamic: author
Dynamic: home-page
Dynamic: license-file
